{
	"comment": "Let's try a week of octagons (3/7)",
	"grid": "octagonal",
	"width": 10,
	"height": 10,
	"wrap": false,
	"tiles": [
		0,
		0,
		0,
		2,
		88,
		132,
		129,
		0,
		0,
		0,
		0,
		0,
		52,
		105,
		166,
		8,
		11,
		52,
		0,
		0,
		0,
		160,
		9,
		72,
		2,
		130,
		80,
		180,
		130,
		0,
		65,
		28,
		69,
		152,
		173,
		36,
		98,
		65,
		128,
		5,
		132,
		48,
		73,
		128,
		150,
		18,
		6,
		104,
		17,
		12,
		200,
		65,
		83,
		65,
		7,
		41,
		82,
		16,
		164,
		44,
		4,
		134,
		66,
		216,
		65,
		84,
		152,
		41,
		4,
		133,
		0,
		130,
		5,
		75,
		66,
		38,
		194,
		82,
		24,
		0,
		0,
		0,
		11,
		129,
		65,
		65,
		72,
		18,
		0,
		0,
		0,
		0,
		0,
		8,
		96,
		8,
		192,
		0,
		0,
		0,
		0,
		0,
		2,
		138,
		10,
		40,
		32,
		0,
		0,
		0,
		0,
		128,
		10,
		40,
		34,
		10,
		32,
		32,
		0,
		0,
		160,
		2,
		168,
		2,
		2,
		32,
		32,
		40,
		8,
		0,
		10,
		32,
		10,
		130,
		10,
		128,
		128,
		8,
		40,
		0,
		2,
		2,
		2,
		32,
		32,
		32,
		160,
		34,
		128,
		0,
		128,
		10,
		162,
		10,
		34,
		162,
		32,
		2,
		128,
		0,
		128,
		10,
		8,
		40,
		128,
		2,
		136,
		160,
		2,
		0,
		0,
		128,
		128,
		34,
		40,
		128,
		40,
		2,
		0,
		0,
		0,
		0,
		32,
		160,
		128,
		130,
		8,
		0,
		0,
		0,
		0,
		0,
		0,
		0,
		0,
		0,
		0,
		0,
		0,
		0
	]
}