{
	"width": 10,
	"height": 10,
	"wrap": true,
	"tiles": [
		2,
		33,
		5,
		18,
		16,
		50,
		7,
		16,
		38,
		24,
		20,
		52,
		12,
		12,
		17,
		1,
		17,
		50,
		36,
		32,
		38,
		11,
		34,
		7,
		34,
		52,
		36,
		17,
		6,
		18,
		29,
		16,
		36,
		6,
		16,
		24,
		40,
		48,
		17,
		38,
		4,
		4,
		3,
		2,
		0,
		0,
		16,
		32,
		5,
		36,
		20,
		0,
		0,
		0,
		0,
		0,
		0,
		0,
		48,
		18,
		50,
		13,
		32,
		1,
		0,
		0,
		1,
		3,
		4,
		36,
		5,
		48,
		18,
		32,
		40,
		26,
		52,
		17,
		26,
		20,
		34,
		5,
		24,
		36,
		5,
		3,
		24,
		3,
		33,
		4,
		33,
		17,
		9,
		8,
		34,
		33,
		17,
		9,
		18,
		6
	],
	"comment": "A little UFO flying by. The aliens get more evil every day (3/7)"
}