{
	"comment": "Random grid, random settings and the meanest puzzle we could manage in 30 seconds. Difficulty: 2.86, best of 4696 attempts.",
	"grid": "hexagonal",
	"width": 17,
	"height": 17,
	"wrap": false,
	"tiles": [
		0,
		0,
		0,
		0,
		6,
		17,
		20,
		14,
		3,
		3,
		34,
		17,
		3,
		0,
		0,
		0,
		0,
		0,
		0,
		0,
		3,
		8,
		45,
		1,
		11,
		52,
		14,
		2,
		25,
		20,
		0,
		0,
		0,
		0,
		0,
		0,
		0,
		40,
		40,
		5,
		17,
		41,
		3,
		29,
		4,
		20,
		14,
		2,
		0,
		0,
		0,
		0,
		0,
		24,
		40,
		6,
		32,
		25,
		8,
		2,
		5,
		3,
		32,
		34,
		8,
		0,
		0,
		0,
		0,
		0,
		20,
		12,
		25,
		34,
		21,
		4,
		48,
		5,
		44,
		3,
		12,
		34,
		2,
		0,
		0,
		0,
		17,
		3,
		34,
		32,
		4,
		11,
		5,
		33,
		2,
		5,
		12,
		5,
		17,
		12,
		0,
		0,
		0,
		1,
		1,
		34,
		52,
		8,
		36,
		30,
		5,
		33,
		40,
		52,
		49,
		44,
		34,
		17,
		0,
		16,
		24,
		20,
		3,
		13,
		3,
		10,
		32,
		8,
		3,
		12,
		40,
		17,
		3,
		17,
		32,
		0,
		12,
		24,
		40,
		50,
		40,
		4,
		34,
		26,
		52,
		34,
		40,
		16,
		33,
		44,
		48,
		38,
		32,
		34,
		23,
		2,
		19,
		8,
		40,
		1,
		20,
		34,
		33,
		20,
		6,
		3,
		34,
		12,
		1,
		0,
		0,
		2,
		21,
		40,
		48,
		17,
		16,
		9,
		32,
		5,
		56,
		16,
		17,
		57,
		36,
		10,
		0,
		0,
		7,
		32,
		12,
		10,
		57,
		52,
		24,
		20,
		17,
		34,
		34,
		34,
		17,
		4,
		0,
		0,
		0,
		0,
		34,
		33,
		3,
		42,
		2,
		17,
		50,
		32,
		34,
		40,
		18,
		1,
		16,
		0,
		0,
		0,
		0,
		5,
		8,
		24,
		21,
		18,
		40,
		40,
		24,
		48,
		37,
		10,
		10,
		0,
		0,
		0,
		0,
		0,
		0,
		17,
		12,
		16,
		10,
		3,
		17,
		6,
		16,
		40,
		34,
		48,
		0,
		0,
		0,
		0,
		0,
		0,
		2,
		20,
		19,
		17,
		18,
		6,
		10,
		10,
		3,
		5,
		0,
		0,
		0,
		0,
		0,
		0,
		0,
		0,
		2,
		3,
		1,
		14,
		5,
		6,
		32,
		24,
		32,
		0,
		0,
		0,
		0
	]
}